pytest_rabbitmq/__init__.py
pytest_rabbitmq/plugin.py
pytest_rabbitmq/py.typed
pytest_rabbitmq/factories/__init__.py
pytest_rabbitmq/factories/client.py
pytest_rabbitmq/factories/executor.py
pytest_rabbitmq/factories/process.py
pytest_rabbitmq-3.1.1.dist-info/AUTHORS.rst
pytest_rabbitmq-3.1.1.dist-info/COPYING
pytest_rabbitmq-3.1.1.dist-info/COPYING.lesser
pytest_rabbitmq-3.1.1.dist-info/METADATA
pytest_rabbitmq-3.1.1.dist-info/WHEEL
pytest_rabbitmq-3.1.1.dist-info/entry_points.txt
pytest_rabbitmq-3.1.1.dist-info/top_level.txt
pytest_rabbitmq-3.1.1.dist-info/zip-safe
pytest_rabbitmq-3.1.1.dist-info/RECORD
