Metadata-Version: 2.1
Name: pytest-rabbitmq
Version: 3.1.1
Summary: RabbitMQ process and client fixtures for pytest
Author-email: Grzegorz Śliwiński <fizyk+pypi@fizyk.dev>
License: GNU LESSER GENERAL PUBLIC LICENSE
Project-URL: Source, https://github.com/ClearcodeHQ/pytest-rabbitmq
Project-URL: Bug Tracker, https://github.com/ClearcodeHQ/pytest-rabbitmq/issues
Project-URL: Changelog, https://github.com/ClearcodeHQ/pytest-rabbitmq/blob/v3.1.1/CHANGES.rst
Keywords: tests,pytest,fixture,rabbitmq,messsage queue
Classifier: Development Status :: 5 - Production/Stable
Classifier: Environment :: Web Environment
Classifier: Intended Audience :: Developers
Classifier: License :: OSI Approved :: GNU Lesser General Public License v3 or later (LGPLv3+)
Classifier: Natural Language :: English
Classifier: Operating System :: OS Independent
Classifier: Programming Language :: Python
Classifier: Programming Language :: Python :: 3
Classifier: Programming Language :: Python :: 3.9
Classifier: Programming Language :: Python :: 3.10
Classifier: Programming Language :: Python :: 3.11
Classifier: Programming Language :: Python :: 3.12
Classifier: Programming Language :: Python :: 3.13
Classifier: Programming Language :: Python :: 3 :: Only
Classifier: Programming Language :: Python :: Implementation :: PyPy
Classifier: Topic :: Software Development :: Libraries :: Python Modules
Classifier: Topic :: Software Development :: Testing
Classifier: Framework :: Pytest
Requires-Python: >=3.9
License-File: COPYING
License-File: COPYING.lesser
License-File: AUTHORS.rst
Requires-Dist: pytest>=6.2
Requires-Dist: port-for>=0.6.0
Requires-Dist: mirakuru
Requires-Dist: pika
